.travis.yml
LICENSE
MANIFEST.in
README.rst
requirements.txt
setup.cfg
setup.py
./nbmerge/__init__.py
nbmerge.egg-info/PKG-INFO
nbmerge.egg-info/SOURCES.txt
nbmerge.egg-info/dependency_links.txt
nbmerge.egg-info/entry_points.txt
nbmerge.egg-info/not-zip-safe
nbmerge.egg-info/top_level.txt
tests/test_merge.py